vcf_annotation_tools/__init__.py
vcf_annotation_tools/vcf_expression_annotator.py
vcf_annotation_tools/vcf_info_annotator.py
vcf_annotation_tools/vcf_readcount_annotator.py
vcf_annotation_tools/vep_annotation_reporter.py
vcf_annotation_tools-3.0.0.dist-info/METADATA
vcf_annotation_tools-3.0.0.dist-info/RECORD
vcf_annotation_tools-3.0.0.dist-info/WHEEL
vcf_annotation_tools-3.0.0.dist-info/entry_points.txt
vcf_annotation_tools-3.0.0.dist-info/top_level.txt
