Metadata-Version: 2.1
Name: vcf-annotation-tools
Version: 3.0.0
Summary: A tool for annotating VCF files with expression and readcount data
Home-page: https://github.com/griffithlab/vcf-annotation-tools
Author: Susanna Kiwala
Author-email: ssiebert@wustl.edu
License: MIT License
Keywords: cancer sequencing variant variants gene expression readcounts VAF allele frequency FPKM TPM transcript VCF
Platform: UNKNOWN
Classifier: Development Status :: 5 - Production/Stable
Classifier: Intended Audience :: Science/Research
Classifier: Topic :: Scientific/Engineering :: Bio-Informatics
Classifier: Programming Language :: Python :: 3.5
Classifier: License :: OSI Approved :: MIT License
Requires-Dist: vcfpy
Requires-Dist: pysam
Requires-Dist: pandas
Requires-Dist: gtfparse
Requires-Dist: testfixtures
